<configs>
<append xpath="/progression/perks/perk[@name='perkAdvancedEngineering']">
	<effect_group>
		<passive_effect name="RecipeTagUnlocked" operation="base_set" level="3,5" value="3" tags="CCTV0-3"/>
		<passive_effect name="RecipeTagUnlocked" operation="base_set" level="3,5" value="3" tags="CCTV4-7"/>
		<passive_effect name="RecipeTagUnlocked" operation="base_set" level="3,5" value="3" tags="CamPan0"/>
		<passive_effect name="RecipeTagUnlocked" operation="base_set" level="3,5" value="3" tags="CamPan1"/>
		<passive_effect name="RecipeTagUnlocked" operation="base_set" level="3,5" value="3" tags="CamPan2"/>
		<passive_effect name="RecipeTagUnlocked" operation="base_set" level="3,5" value="3" tags="CamPan3"/>
		<passive_effect name="RecipeTagUnlocked" operation="base_set" level="3,5" value="3" tags="CamPan4"/>
		<passive_effect name="RecipeTagUnlocked" operation="base_set" level="3,5" value="3" tags="CamPan5"/>
		<passive_effect name="RecipeTagUnlocked" operation="base_set" level="3,5" value="3" tags="CamPan6"/>
		<passive_effect name="RecipeTagUnlocked" operation="base_set" level="3,5" value="3" tags="CamPan6"/>
		<passive_effect name="RecipeTagUnlocked" operation="base_set" level="3,5" value="3" tags="CCTVLarge0-3"/>
		<passive_effect name="RecipeTagUnlocked" operation="base_set" level="3,5" value="3" tags="CCTVLarge4-7"/>
		<passive_effect name="RecipeTagUnlocked" operation="base_set" level="3,5" value="3" tags="CamPanSm0"/>
		<passive_effect name="RecipeTagUnlocked" operation="base_set" level="3,5" value="3" tags="CamPanSm1"/>
		<passive_effect name="RecipeTagUnlocked" operation="base_set" level="3,5" value="3" tags="CamPanSm2"/>
		<passive_effect name="RecipeTagUnlocked" operation="base_set" level="3,5" value="3" tags="CamPanSm3"/>
		<passive_effect name="RecipeTagUnlocked" operation="base_set" level="3,5" value="3" tags="CamPanSm4"/>
		<passive_effect name="RecipeTagUnlocked" operation="base_set" level="3,5" value="3" tags="CamPanSm5"/>
		<passive_effect name="RecipeTagUnlocked" operation="base_set" level="3,5" value="3" tags="CamPanSm6"/>
		<passive_effect name="RecipeTagUnlocked" operation="base_set" level="3,5" value="3" tags="CamPanSm7"/>
		
	</effect_group>
</append>
</configs>