<configs>
<append xpath="/blocks">
<!-- Horses -->
<block name="AppleBlock">
		<property name="CustomIcon" value="buttercup" />
		<property name="CreativeMode" value="Player"/>
		<property name="DisplayType" value="blockMulti"/>
		<property name="Material" value="Mplants"/>
		<property name="LightOpacity" value="0"/>
		<property name="Shape" value="ModelEntity"/>	
		<property name="Model" value="#@modfolder:Resources/TelricsHorses.unity3d?AppleBlockPrefab"/>
		<property name="MultiBlockDim" value="1,1,1"/>
		<property name="ImposterDontBlock" value="true"/>
		<property name="Collide" value="melee"/>
		<property name="IsTerrainDecoration" value="true"/>
		<property name="HarvestOverdamage" value="false"/>
		<drop event="Destroy" name="foodApple" count="1"/>
		<drop event="Fall" name="foodApple" count="1" prob="1" stick_chance="0"/>
		<property name="FilterTags" value="foutdoor,fcrops"/>
		<property name="SortOrder1" value="a090"/>
		<property name="SortOrder2" value="0002"/>
	</block>
<block name="CarrotBlock">
		<property name="CustomIcon" value="buttercup" />
		<property name="CreativeMode" value="Player"/>
		<property name="DisplayType" value="blockMulti"/>
		<property name="Material" value="Mplants"/>
		<property name="LightOpacity" value="0"/>
		<property name="Shape" value="ModelEntity"/>	
		<property name="Model" value="#@modfolder:Resources/TelricsHorses.unity3d?CarrotBlockPrefab"/>
		<property name="MultiBlockDim" value="1,1,1"/>
		<property name="ImposterDontBlock" value="true"/>
		<property name="Collide" value="melee"/>
		<property name="IsTerrainDecoration" value="true"/>
		<property name="HarvestOverdamage" value="false"/>
		<drop event="Destroy" name="foodCarrot" count="1"/>
		<drop event="Fall" name="foodCarrot" count="1" prob="1" stick_chance="0"/>
		<property name="FilterTags" value="foutdoor,fcrops"/>
		<property name="SortOrder1" value="a090"/>
		<property name="SortOrder2" value="0002"/>
	</block>

<!-- tests -->
</append>

<append xpath="/blocks/block[@name='treeMaster']">
	<drop event="Harvest" name="foodApple" prob="0.5" count="10" tag="allHarvest"/>
</append>








</configs>